rtl/compute/mac.sv
`default_nettype none

`timescale 1ns/1ps

// MAC n cheese
// MAC(book) ew!


//signal priority hierarchy:: freeze > load(first) > add(valid) > hold

//control read acc when done is high

module mac(

    input logic clk,
    input logic rst,
    input logic valid,
    input logic first, //fresh new data, loads the product calculated this cycle right into acc to replace current acc

    input logic last, //giving upper level fsm a flag to tell it basically that ts data is all ready

    input logic freeze, //freeze the entire mac, all 3 pipelines

    input logic signed [7:0] weight,
    input logic unsigned [7:0] activation,

    output logic signed [31:0] acc, //beat in cycle t, acc valid in cycle t+3
    output logic valid_out,
    output logic done
);


logic signed [7:0] w_r;
logic signed [8:0] act_r;
logic valid_s1;

logic signed [16:0] prod_r;
logic valid_s2;

logic first_s1;
logic first_s2;

logic last_s1, last_s2;




always_ff @(posedge clk, posedge rst) begin

    if (rst) begin

        w_r <= 8'b0;
        act_r <= 9'b0;
        valid_s1 <= 1'b0;

        valid_out <= 1'b0;
        acc <= 32'b0;

        prod_r <= 17'b0;
        valid_s2 <= 1'b0;

        first_s1 <= 1'b0;
        first_s2 <= 1'b0;

        last_s1 <= 1'b0;
        last_s2 <= 1'b0;
        done <= 1'b0;
    end

    else begin

        //pipeline stage uno


        w_r <= (freeze) ? w_r : weight;
        act_r <= (freeze) ? act_r : {1'b0, activation};

        valid_s1 <= (freeze) ? valid_s1 : valid;

        first_s1 <= (freeze) ? first_s1 : first;
        last_s1 <= (freeze) ? last_s1 : last;

        

        //pipeline stage deux


        valid_s2 <= (freeze) ? valid_s2 : valid_s1;
        prod_r <= (freeze) ? prod_r : (w_r * act_r);

        first_s2 <= (freeze) ? first_s2 : first_s1;
        last_s2 <= (freeze) ? last_s2 : last_s1;

        //pipeline stage 3

        if (freeze) acc <= acc;
        else if (valid_s2 && first_s2) acc <= {{15{prod_r[16]}}, prod_r};
        else if (valid_s2) acc <= acc + {{15{prod_r[16]}}, prod_r};

        
        
        valid_out <= (freeze) ? 1'b0 : valid_s2;
        done <= (freeze) ? 1'b0 : (valid_s2 && last_s2);

    end


end



endmodule


`default_nettype wire

sim/tb_mac.sv
`timescale 1ns/1ps
`default_nettype none




module tb_mac;

    logic clk = 0, rst = 1;


    logic valid = 0;
    logic first = 0;
    logic last = 0;
    logic freeze = 0;

    logic signed [7:0] weight = 0;
    logic [7:0] activation = 0;


    logic signed [31:0] acc;

    logic valid_out;
    logic done;

    int checks = 0;
    int fails = 0;
    int t = 0;

    logic got = 0;

    mac dut (.clk(clk),
             .rst(rst), 
             .valid(valid), 
             .first(first), 
             .last(last),
             .freeze(freeze), 
             .weight(weight),
             .activation(activation),
             .acc(acc),
             .valid_out(valid_out),
             .done(done)
             );



    always #5 clk = ~clk; // 100 MHz clk (10ns clkperiod)



    task tick(); 
        
        @(posedge clk) #1; 
        
    endtask


    task beat(input signed [7:0] w, input [7:0] a, input logic f, input logic l);

        weight = w; 
        activation = a; 
        first = f; 
        last = l; 
        valid = 1;

        tick();

        valid = 0;
        first = 0;
        last = 0;
        weight = 0;
        activation = 0;

    endtask



    task wait_done(input int limit);

        t = 0;
        got = 0;

        while (t < limit && !got) begin 
            tick(); t = t + 1; 
            if (done) got = 1; 
        end
        
            if (!got) begin
            checks = checks + 1;
            fails = fails + 1;
            $display("FAIL  not done in %0d ticks", limit);
        end
    endtask



    task check_acc(input signed [31:0] want, input string what);

        checks = checks + 1;


        if (acc !== want) begin
            fails = fails + 1;
            $display("FAIL  %-46s acc = %0d, wanted %0d", what, acc, want);
        
        end else $display("pass  %-46s acc = %0d", what, acc);
            
    endtask



    task check_flags(input logic wd, input logic wv, input string what);

        checks = checks + 1;


        if (done !== wd || valid_out !== wv) begin

            fails = fails + 1;
            $display("FAIL  %-46s done=%b valid_out=%b", what, done, valid_out);

        end 

        else $display("pass  %-46s done=%b valid_out=%b", what, done, valid_out);

    endtask



    initial begin

        $dumpfile("sim/tb_mac.vcd");        // run from the project root
        $dumpvars(0, tb_mac);

        repeat(3) tick();
        rst = 0; 
        tick();



        //reset 
        $display("\n[1] reset");
        check_acc(0, "acc is 0 after reset");
        check_flags(1'b0, 1'b0, "done and valid_out are 0 after reset");



        // single beat first=1 and last=1
        $display("\n[2] single beat (first=1, last=1)");

        beat(8'sd3, 8'd7, 1'b1, 1'b1);  
        wait_done(20);  
        check_acc(21, "+3 x +7");

        beat(-8'sd3, 8'd7, 1'b1, 1'b1);  
        wait_done(20);  
        check_acc(-21, "-3 x +7");

        beat(-8'sd128, 8'd255, 1'b1, 1'b1);  
        wait_done(20);  
        check_acc(-32640, "-128 x 255 (extreme)");

        beat(-8'sd3, 8'd249, 1'b1, 1'b1);  
        wait_done(20);  
        check_acc(-747, "-3 x 249 (249 is -7 unsigned)");



        // several beats into ONE dot product
        $display("\n[3] three beats: 2x5 + 4x5 + 6x5 = 10 + 20 + 30");

        beat(8'sd2, 8'd5, 1'b1, 1'b0);
        beat(8'sd4, 8'd5, 1'b0, 1'b0);
        beat(8'sd6, 8'd5, 1'b0, 1'b1);

        wait_done(20);
        check_acc(60, "sum of the three products");



        // first=1 starts a NEW sum
        $display("\n[4] a new batch with first=1 wipes the previous sum");
        beat(8'sd7, 8'd2, 1'b1, 1'b1);
        wait_done(20);
        check_acc(14, "new sum only: the old 60 must be gone");



        // valid=0 means the beat is ignored
        $display("\n[5] junk on the bus with valid=0 must do nothing");

        beat(8'sd5, 8'd5, 1'b1, 1'b1);
        wait_done(20);
        check_acc(25, "baseline");

        valid = 0; 
        first = 0; 
        last = 0; 
        weight = -8'sd128; 
        activation = 8'd255;

        tick();

        weight = 0; 
        activation = 0;

        repeat(4) tick();
        check_acc(25, "unchanged after a tick with valid=0");



        // first/last are meaningless without valid
        $display("\n[6] first=1 and last=1 but valid=0 must do nothing");

        valid = 0; 
        first = 1; 
        last = 1; 
        weight = -8'sd128; 
        activation = 8'd255;

        tick();

        first = 0; 
        last = 0; 
        weight = 0; 
        activation = 0;

        repeat(4) tick();
        check_acc(25, "unchanged after a stray first/last with valid=0");



        // freeze holds EVERYTHING
        $display("\n[7] freeze in the middle of a sum");
        beat(8'sd2, 8'd5, 1'b1, 1'b0);
        beat(8'sd4, 8'd5, 1'b0, 1'b0);

        repeat(4) tick();

        check_acc(30, "two beats accumulated before the freeze");
        freeze = 1;

        repeat(3) begin
            tick();
            check_acc(30, "acc holds while frozen");
            check_flags(1'b0, 1'b0, "done stays 0 while frozen");
        end

        freeze = 0;



        // a beat held across a freeze is not lost
        $display("\n[8] final beat held across a freeze");

        weight = 8'sd6; 
        activation = 8'd5; 
        first = 0; 
        last = 1; 
        valid = 1;
        freeze = 1;

        repeat(3) tick();
        freeze = 0;
        tick();

        valid = 0; 
        last = 0; 
        weight = 0; 
        activation = 0;

        wait_done(20);
        check_acc(60, "held final beat landed: 30 + 30");



        // freeze while a batch is in flight
        $display("\n[9] freeze while a batch is in flight");

        beat(8'sd1, 8'd2, 1'b1, 1'b0);
        beat(8'sd1, 8'd4, 1'b0, 1'b0);
        beat(8'sd1, 8'd6, 1'b0, 1'b1);

        tick();                              
        check_flags(1'b0, 1'b1, "in the window: valid_out high, done low");

        freeze = 1;

        repeat(2) begin
            tick();
            check_flags(1'b0, 1'b0, "frozen: acc did not change, so valid_out must be 0");
        end

        freeze = 0;
        wait_done(20);
        check_acc(12, "batch completed: 2 + 4 + 6");



        // summary

        $display("\n==================================================");

        $display("  checks: %0d    failures: %0d", checks, fails);
        if (fails == 0) $display("  RESULT: ALL PASS");
        else $display("  RESULT: *** %0d FAILURES ***", fails);

        $display("==================================================\n");

        if (checks < 20) $fatal(1, "only %0d checks ran, the suite did not exercise the design", checks);
        if (fails != 0) $fatal(1, "verification failed");

        $finish;

    end


endmodule


`default_nettype wire

sim/tb_mac.vcd
$version Generated by VerilatedVcd $end
$timescale 1ps $end
 $scope module $rootio $end
 $upscope $end
 $scope module tb_mac $end
  $var wire 1 : clk $end
  $var wire 1 # rst $end
  $var wire 1 $ valid $end
  $var wire 1 % first $end
  $var wire 1 & last $end
  $var wire 1 ' freeze $end
  $var wire 8 ( weight [7:0] $end
  $var wire 8 ) activation [7:0] $end
  $var wire 32 . acc [31:0] $end
  $var wire 1 / valid_out $end
  $var wire 1 0 done $end
  $var wire 32 * checks [31:0] $end
  $var wire 32 + fails [31:0] $end
  $var wire 32 , t [31:0] $end
  $var wire 1 - got $end
  $scope module dut $end
   $var wire 1 : clk $end
   $var wire 1 # rst $end
   $var wire 1 $ valid $end
   $var wire 1 % first $end
   $var wire 1 & last $end
   $var wire 1 ' freeze $end
   $var wire 8 ( weight [7:0] $end
   $var wire 8 ) activation [7:0] $end
   $var wire 32 . acc [31:0] $end
   $var wire 1 / valid_out $end
   $var wire 1 0 done $end
   $var wire 8 1 w_r [7:0] $end
   $var wire 9 2 act_r [8:0] $end
   $var wire 1 3 valid_s1 $end
   $var wire 17 4 prod_r [16:0] $end
   $var wire 1 5 valid_s2 $end
   $var wire 1 6 first_s1 $end
   $var wire 1 7 first_s2 $end
   $var wire 1 8 last_s1 $end
   $var wire 1 9 last_s2 $end
  $upscope $end
 $upscope $end
$enddefinitions $end


#0
1#
0$
0%
0&
0'
b00000000 (
b00000000 )
b00000000000000000000000000000000 *
b00000000000000000000000000000000 +
b00000000000000000000000000000000 ,
0-
b00000000000000000000000000000000 .
0/
00
b00000000 1
b000000000 2
03
b00000000000000000 4
05
06
07
08
09
0:
#5000
1:
#6000
#10000
0:
#15000
1:
#16000
#20000
0:
#25000
1:
#26000
0#
#30000
0:
#35000
1:
#36000
1$
1%
1&
b00000011 (
b00000111 )
b00000000000000000000000000000010 *
#40000
0:
#45000
b00000011 1
b000000111 2
13
16
18
1:
#46000
0$
0%
0&
b00000000 (
b00000000 )
#50000
0:
#55000
b00000000 1
b000000000 2
03
b00000000000010101 4
15
06
17
08
19
1:
#56000
b00000000000000000000000000000001 ,
#60000
0:
#65000
b00000000000000000000000000010101 .
1/
10
b00000000000000000 4
05
07
09
1:
#66000
1$
1%
1&
b11111101 (
b00000111 )
b00000000000000000000000000000011 *
b00000000000000000000000000000010 ,
1-
#70000
0:
#75000
0/
00
b11111101 1
b000000111 2
13
16
18
1:
#76000
0$
0%
0&
b00000000 (
b00000000 )
b00000000000000000000000000000000 ,
0-
#80000
0:
#85000
b00000000 1
b000000000 2
03
b11111111111101011 4
15
06
17
08
19
1:
#86000
b00000000000000000000000000000001 ,
#90000
0:
#95000
b11111111111111111111111111101011 .
1/
10
b00000000000000000 4
05
07
09
1:
#96000
1$
1%
1&
b10000000 (
b11111111 )
b00000000000000000000000000000100 *
b00000000000000000000000000000010 ,
1-
#100000
0:
#105000
0/
00
b10000000 1
b011111111 2
13
16
18
1:
#106000
0$
0%
0&
b00000000 (
b00000000 )
b00000000000000000000000000000000 ,
0-
#110000
0:
#115000
b00000000 1
b000000000 2
03
b11000000010000000 4
15
06
17
08
19
1:
#116000
b00000000000000000000000000000001 ,
#120000
0:
#125000
b11111111111111111000000010000000 .
1/
10
b00000000000000000 4
05
07
09
1:
#126000
1$
1%
1&
b11111101 (
b11111001 )
b00000000000000000000000000000101 *
b00000000000000000000000000000010 ,
1-
#130000
0:
#135000
0/
00
b11111101 1
b011111001 2
13
16
18
1:
#136000
0$
0%
0&
b00000000 (
b00000000 )
b00000000000000000000000000000000 ,
0-
#140000
0:
#145000
b00000000 1
b000000000 2
03
b11111110100010101 4
15
06
17
08
19
1:
#146000
b00000000000000000000000000000001 ,
#150000
0:
#155000
b11111111111111111111110100010101 .
1/
10
b00000000000000000 4
05
07
09
1:
#156000
1$
1%
b00000010 (
b00000101 )
b00000000000000000000000000000110 *
b00000000000000000000000000000010 ,
1-
#160000
0:
#165000
0/
00
b00000010 1
b000000101 2
13
16
1:
#166000
0%
b00000100 (
#170000
0:
#175000
b00000100 1
b00000000000001010 4
15
06
17
1:
#176000
1&
b00000110 (
#180000
0:
#185000
b00000000000000000000000000001010 .
1/
b00000110 1
b00000000000010100 4
07
18
1:
#186000
0$
0&
b00000000 (
b00000000 )
b00000000000000000000000000000000 ,
0-
#190000
0:
#195000
b00000000000000000000000000011110 .
b00000000 1
b000000000 2
03
b00000000000011110 4
08
19
1:
#196000
b00000000000000000000000000000001 ,
#200000
0:
#205000
b00000000000000000000000000111100 .
10
b00000000000000000 4
05
09
1:
#206000
1$
1%
1&
b00000111 (
b00000010 )
b00000000000000000000000000000111 *
b00000000000000000000000000000010 ,
1-
#210000
0:
#215000
0/
00
b00000111 1
b000000010 2
13
16
18
1:
#216000
0$
0%
0&
b00000000 (
b00000000 )
b00000000000000000000000000000000 ,
0-
#220000
0:
#225000
b00000000 1
b000000000 2
03
b00000000000001110 4
15
06
17
08
19
1:
#226000
b00000000000000000000000000000001 ,
#230000
0:
#235000
b00000000000000000000000000001110 .
1/
10
b00000000000000000 4
05
07
09
1:
#236000
1$
1%
1&
b00000101 (
b00000101 )
b00000000000000000000000000001000 *
b00000000000000000000000000000010 ,
1-
#240000
0:
#245000
0/
00
b00000101 1
b000000101 2
13
16
18
1:
#246000
0$
0%
0&
b00000000 (
b00000000 )
b00000000000000000000000000000000 ,
0-
#250000
0:
#255000
b00000000 1
b000000000 2
03
b00000000000011001 4
15
06
17
08
19
1:
#256000
b00000000000000000000000000000001 ,
#260000
0:
#265000
b00000000000000000000000000011001 .
1/
10
b00000000000000000 4
05
07
09
1:
#266000
b10000000 (
b11111111 )
b00000000000000000000000000001001 *
b00000000000000000000000000000010 ,
1-
#270000
0:
#275000
0/
00
b10000000 1
b011111111 2
1:
#276000
b00000000 (
b00000000 )
#280000
0:
#285000
b00000000 1
b000000000 2
b11000000010000000 4
1:
#286000
#290000
0:
#295000
b00000000000000000 4
1:
#296000
#300000
0:
#305000
1:
#306000
#310000
0:
#315000
1:
#316000
1%
1&
b10000000 (
b11111111 )
b00000000000000000000000000001010 *
#320000
0:
#325000
b10000000 1
b011111111 2
16
18
1:
#326000
0%
0&
b00000000 (
b00000000 )
#330000
0:
#335000
b00000000 1
b000000000 2
b11000000010000000 4
06
17
08
19
1:
#336000
#340000
0:
#345000
b00000000000000000 4
07
09
1:
#346000
#350000
0:
#355000
1:
#356000
#360000
0:
#365000
1:
#366000
1$
1%
b00000010 (
b00000101 )
b00000000000000000000000000001011 *
#370000
0:
#375000
b00000010 1
b000000101 2
13
16
1:
#376000
0%
b00000100 (
#380000
0:
#385000
b00000100 1
b00000000000001010 4
15
06
17
1:
#386000
0$
b00000000 (
b00000000 )
#390000
0:
#395000
b00000000000000000000000000001010 .
1/
b00000000 1
b000000000 2
03
b00000000000010100 4
07
1:
#396000
#400000
0:
#405000
b00000000000000000000000000011110 .
b00000000000000000 4
05
1:
#406000
#410000
0:
#415000
0/
1:
#416000
#420000
0:
#425000
1:
#426000
1'
b00000000000000000000000000001100 *
#430000
0:
#435000
1:
#436000
b00000000000000000000000000001110 *
#440000
0:
#445000
1:
#446000
b00000000000000000000000000010000 *
#450000
0:
#455000
1:
#456000
1$
1&
b00000110 (
b00000101 )
b00000000000000000000000000010010 *
#460000
0:
#465000
1:
#466000
#470000
0:
#475000
1:
#476000
#480000
0:
#485000
1:
#486000
0'
#490000
0:
#495000
b00000110 1
b000000101 2
13
18
1:
#496000
0$
0&
b00000000 (
b00000000 )
b00000000000000000000000000000000 ,
0-
#500000
0:
#505000
b00000000 1
b000000000 2
03
b00000000000011110 4
15
08
19
1:
#506000
b00000000000000000000000000000001 ,
#510000
0:
#515000
b00000000000000000000000000111100 .
1/
10
b00000000000000000 4
05
09
1:
#516000
1$
1%
b00000001 (
b00000010 )
b00000000000000000000000000010011 *
b00000000000000000000000000000010 ,
1-
#520000
0:
#525000
0/
00
b00000001 1
b000000010 2
13
16
1:
#526000
0%
b00000100 )
#530000
0:
#535000
b000000100 2
b00000000000000010 4
15
06
17
1:
#536000
1&
b00000110 )
#540000
0:
#545000
b00000000000000000000000000000010 .
1/
b000000110 2
b00000000000000100 4
07
18
1:
#546000
0$
0&
b00000000 (
b00000000 )
#550000
0:
#555000
b00000000000000000000000000000110 .
b00000000 1
b000000000 2
03
b00000000000000110 4
08
19
1:
#556000
1'
b00000000000000000000000000010100 *
#560000
0:
#565000
0/
1:
#566000
b00000000000000000000000000010101 *
#570000
0:
#575000
1:
#576000
0'
b00000000000000000000000000010110 *
b00000000000000000000000000000000 ,
0-
#580000
0:
#585000
b00000000000000000000000000001100 .
1/
10
b00000000000000000 4
05
09
1:
#586000
b00000000000000000000000000010111 *
b00000000000000000000000000000001 ,
1-
